concoursepy/__init__.py
concoursepy/api.py
concoursepy-0.0.20.dist-info/LICENSE
concoursepy-0.0.20.dist-info/METADATA
concoursepy-0.0.20.dist-info/WHEEL
concoursepy-0.0.20.dist-info/top_level.txt
concoursepy-0.0.20.dist-info/RECORD
