Metadata-Version: 2.1
Name: concoursepy
Version: 0.0.20
Summary: library to interface with concourse
Home-page: https://github.com/arwineap/concoursepy
Author: Alex Arwine
Author-email: arwineap@gmail.com
License: UNKNOWN
Platform: UNKNOWN
Classifier: Programming Language :: Python :: 3
Classifier: License :: OSI Approved :: MIT License
Classifier: Operating System :: OS Independent
Requires-Dist: requests
Requires-Dist: sseclient-py
